{
  "animateLoading": true,
  "backgroundColor": "#FFFFFF",
  "borderColor": "#E0DEDE",
  "borderRadius": "{{appsmith.theme.borderRadius.appBorderRadius}}",
  "borderWidth": "1",
  "bottomRow": 46,
  "boxShadow": "{{appsmith.theme.boxShadow.appBoxShadow}}",
  "children": [
    {
      "bottomRow": 450,
      "canExtend": false,
      "containerStyle": "none",
      "detachFromLayout": true,
      "displayName": "Canvas",
      "dynamicBindingPathList": [],
      "flexLayers": [],
      "hideCard": true,
      "isDeprecated": false,
      "isLoading": false,
      "isVisible": true,
      "key": "d5578ydpdj",
      "leftColumn": 0,
      "minHeight": 400,
      "minWidth": 450,
      "mobileBottomRow": 400,
      "mobileLeftColumn": 0,
      "mobileRightColumn": 139.71875,
      "mobileTopRow": 0,
      "parentColumnSpace": 1,
      "parentId": "pg2u7o8ulx",
      "parentRowSpace": 1,
      "renderMode": "CANVAS",
      "responsiveBehavior": "fill",
      "rightColumn": 139.71875,
      "topRow": 0,
      "type": "CANVAS_WIDGET",
      "version": 1,
      "widgetId": "n3ruu0li1y",
      "widgetName": "Canvas11"
    }
  ],
  "displayName": "Form",
  "dynamicBindingPathList": [
    {
      "key": "borderRadius"
    },
    {
      "key": "boxShadow"
    }
  ],
  "dynamicHeight": "FIXED",
  "dynamicTriggerPathList": [],
  "hideCard": false,
  "iconSVG": "/static/media/icon.ea3e08d130e59c56867ae40114c10eed.svg",
  "isCanvas": true,
  "isDeprecated": false,
  "isLoading": false,
  "isVisible": true,
  "key": "18fnd0o1r6",
  "leftColumn": 0,
  "maxDynamicHeight": 9000,
  "minDynamicHeight": 10,
  "minWidth": 450,
  "mobileBottomRow": 41,
  "mobileLeftColumn": 0,
  "mobileRightColumn": 17,
  "mobileTopRow": 1,
  "parentColumnSpace": 8.21875,
  "parentId": "od6ks7ebva",
  "parentRowSpace": 10,
  "positioning": "fixed",
  "renderMode": "CANVAS",
  "responsiveBehavior": "fill",
  "rightColumn": 64,
  "searchTags": [
    "group"
  ],
  "shouldScrollContents": false,
  "topRow": 1,
  "type": "FORM_WIDGET",
  "widgetId": "pg2u7o8ulx",
  "widgetName": "Form2"
}