{
  "gitSyncId": "67ed4b9f478f7245ca44d697_4c6aa566-7008-4ee5-b7e9-5b204fe0f801",
  "id": "View Applications_rejectLoan",
  "pluginId": "postgres-plugin",
  "pluginType": "DB",
  "unpublishedAction": {
    "actionConfiguration": {
      "body": "UPDATE loan_application\n  SET status = 'Rejected',\n\treason = {{inp_rejectReason.text}}\n  WHERE id = {{ tbl_applications.selectedRow.Id }};\n",
      "encodeParamsToggle": true,
      "paginationType": "NONE",
      "pluginSpecifiedTemplates": [
        {
          "value": true
        }
      ],
      "timeoutInMillisecond": 10000
    },
    "confirmBeforeExecute": false,
    "datasource": {
      "id": "Sample Database",
      "isAutoGenerated": false,
      "name": "Sample Database",
      "pluginId": "postgres-plugin"
    },
    "dynamicBindingPathList": [
      {
        "key": "body"
      }
    ],
    "executeOnLoad": false,
    "name": "rejectLoan",
    "pageId": "View Applications",
    "userSetOnLoad": false
  }
}